LICENSE
MANIFEST.in
README.rst
setup.py
x_x/__init__.py
x_x/_version.py
x_x/asciitable.py
x_x/compat.py
x_x/cursor.py
x_x/x_x.py
x_x.egg-info/PKG-INFO
x_x.egg-info/SOURCES.txt
x_x.egg-info/dependency_links.txt
x_x.egg-info/entry_points.txt
x_x.egg-info/requires.txt
x_x.egg-info/top_level.txt