Metadata-Version: 1.1
Name: x-x
Version: 0.9
Summary: Excel file CLI Reader
Home-page: http://github.com/krockode/x_x
Author: Kristian Perkins
Author-email: khperkins@gmail.com
License: Apache 2.0
Platform: UNKNOWN
Classifier: Environment :: Console
Classifier: Development Status :: 3 - Alpha
Classifier: License :: OSI Approved :: Apache Software License
